galaxychop-0.2.dist-info/METADATA
galaxychop-0.2.dist-info/LICENSE.txt
galaxychop-0.2.dist-info/WHEEL
galaxychop-0.2.dist-info/RECORD
galaxychop-0.2.dist-info/top_level.txt
galaxychop.libs/libgfortran-2e0d59d6.so.5.0.0
galaxychop.libs/libquadmath-2d0c479f.so.0.0.0
galaxychop.libs/libgomp-f7e03b3e.so.1.0.0
galaxychop/__init__.py
galaxychop/data.py
galaxychop/plot.py
galaxychop/io.py
galaxychop/models/_kmeans.py
galaxychop/models/__init__.py
galaxychop/models/_base.py
galaxychop/models/_gaussian_mixture.py
galaxychop/models/_histogram.py
galaxychop/models/_threshold.py
galaxychop/utils/_center.py
galaxychop/utils/__init__.py
galaxychop/utils/_decorators.py
galaxychop/utils/_circ.py
galaxychop/utils/_align.py
galaxychop/utils/_potential.py
galaxychop/utils/fortran/potential.cpython-39-x86_64-linux-gnu.so
galaxychop/utils/fortran/__init__.py
