Metadata-Version: 2.1
Name: galaxychop
Version: 0.2
Summary: Galaxy dynamic de-composition
Home-page: https://github.com/vcristiani/galaxy-chop
Author: Valeria Cristiani et al
Author-email: valeria.cristiani@unc.edu.ar
License: MIT
Keywords: galaxy,dynamics
Platform: UNKNOWN
Classifier: Development Status :: 4 - Beta
Classifier: Intended Audience :: Education
Classifier: Intended Audience :: Science/Research
Classifier: License :: OSI Approved :: MIT License
Classifier: Operating System :: OS Independent
Classifier: Programming Language :: Python
Classifier: Programming Language :: Python :: 3
Classifier: Programming Language :: Python :: 3.7
Classifier: Programming Language :: Python :: 3.8
Classifier: Programming Language :: Python :: 3.9
Classifier: Programming Language :: Python :: Implementation :: CPython
Classifier: Topic :: Scientific/Engineering
License-File: LICENSE.txt
Requires-Dist: numpy (>=1.13.3)
Requires-Dist: scipy (>=1.0)
Requires-Dist: scikit-learn
Requires-Dist: astropy
Requires-Dist: uttrs
Requires-Dist: pandas
Requires-Dist: h5py
Requires-Dist: custom-inherit
Requires-Dist: seaborn
